LICENSE
MANIFEST.in
README.rst
distribute_setup.py
setup.py
coinor/__init__.py
coinor.pulp.egg-info/PKG-INFO
coinor.pulp.egg-info/SOURCES.txt
coinor.pulp.egg-info/dependency_links.txt
coinor.pulp.egg-info/namespace_packages.txt
coinor.pulp.egg-info/not-zip-safe
coinor.pulp.egg-info/requires.txt
coinor.pulp.egg-info/top_level.txt
coinor/pulp/__init__.py