Metadata-Version: 1.0
Name: coinor.pulp
Version: 1.0.4
Summary: This is a package that wraps pulp and imports it into the namespace
Home-page: http://www.coin-or.org/PuLP/
Author: Stuart Mitchell
Author-email: s.mitchell@auckland.ac.nz
License: Copyright (c) 2010, Stuart Mitchell
